gcp_integration_tools/CloudFunction.py
gcp_integration_tools/__init__.py
gcp_integration_tools/lib/__init__.py
gcp_integration_tools/lib/utilities.py
pypi_test/CloudFunction.py
pypi_test/__init__.py
pypi_test/__main__.py
pypi_test/lib/__init__.py
pypi_test/lib/utilities.py
gcp_integration_tools-0.0.1.dist-info/METADATA
gcp_integration_tools-0.0.1.dist-info/WHEEL
gcp_integration_tools-0.0.1.dist-info/top_level.txt
gcp_integration_tools-0.0.1.dist-info/RECORD
